pix2py/__init__.py
pix2py/pix2py.py
pix2py-1.0.1.dist-info/LICENSE
pix2py-1.0.1.dist-info/METADATA
pix2py-1.0.1.dist-info/WHEEL
pix2py-1.0.1.dist-info/RECORD
