Metadata-Version: 2.3
Name: pix2py
Version: 1.0.1
Summary: A python package to plot pixelmaps generated by Domino.
License: GPL-3.0
Author: Philip Hartmeier
Author-email: philip.hartmeier@hotmail.com
Requires-Python: >=3.10,<4.0
Classifier: License :: OSI Approved :: GNU General Public License v3 (GPLv3)
Classifier: Programming Language :: Python :: 3
Classifier: Programming Language :: Python :: 3.10
Classifier: Programming Language :: Python :: 3.11
Classifier: Programming Language :: Python :: 3.12
Classifier: Programming Language :: Python :: 3.13
Requires-Dist: ipykernel (>=6.29.0,<7.0.0)
Requires-Dist: matplotlib (>=3.8.2,<4.0.0)
Requires-Dist: numpy (>=1.26.3,<2.0.0)
Requires-Dist: pandas (>=2.2.0,<3.0.0)
